{
	"STATUS_CODE": 200,
	"REQUEST": {
		"params": {}
	},
	"RESPONSE": {
		"ts": 1400604242301,
		"layout": [{
			"items": [{
				"value": {
					"sticky": false,
					"showVoice": true,
					"showBarCode": true,
					"searchHint": "Search for products and brands"
				},
				"action": {
					"screenType": "searchPage",
					"omnitureData": "SearchWidget"
				}
			}],
			"type": "SearchWidget",
			"pageNumber": -1,
			"slotNumber": -1,
			"title": "Search",
			"ts": 1400604242301,
			"id": "14c718ceef9c6d76e9e859c0d6a761b5"
		}, {
			"items": [{
				"action": {
					"screenType": "productListView",
					"omnitureData": "BannerWidget",
					"originalUrl": "/laptops/pr?offer=MultitierLaptop_Offer_Main.&sid=6bo,b5g",
					"url": "/laptops/pr?offer=MultitierLaptop_Offer_Main.&sid=6bo,b5g",
					"params": {
						"store": "6bo/b5g",
						"filter": "filter=facets.promo%255B%255D%3DMultitierLaptop_Offer_Main.",
						"valid": true
					}
				},
				"value": {
					"image": {
						"240": "http://img6a.flixcart.com/www/promos/new/20140520-140332-mobile-small-10.jpg",
						"320": "http://img6a.flixcart.com/www/promos/new/20140520-140332-mobile-medium-10.jpg",
						"480": "http://img5a.flixcart.com/www/promos/new/20140520-140332-mobile-large-11.jpg",
						"720": "http://img6a.flixcart.com/www/promos/new/20140520-140332-mobile-extra-large-12.jpg"
					},
					"source": "config"
				}
			}, {
				"action": {
					"screenType": "productListView",
					"omnitureData": "BannerWidget",
					"originalUrl": "/beauty-and-personal-care/fragrances/perfumes/~flat-50-off/pr?p[]=sort=popularity&sid=t06,r3o,aa1",
					"url": "/beauty-and-personal-care/fragrances/perfumes/~flat-50-off/pr?p[]=sort=popularity&sid=t06,r3o,aa1",
					"params": {
						"store": "t06/r3o/aa1",
						"tag": "tag=tags%255B%255D%3Dflat-50-off",
						"sort": "sort=sort%3Dpopularity",
						"valid": true
					}
				},
				"value": {
					"image": {
						"240": "http://img5a.flixcart.com/www/promos/new/20140519-113337-mobile-small.jpg",
						"320": "http://img5a.flixcart.com/www/promos/new/20140519-113337-mobile-medium.jpg",
						"480": "http://img5a.flixcart.com/www/promos/new/20140519-113337-mobile-large.jpg",
						"720": "http://img6a.flixcart.com/www/promos/new/20140519-113337-mobile-extra-large.jpg"
					},
					"source": "config"
				}
			}, {
				"action": {
					"screenType": "productListView",
					"omnitureData": "BannerWidget",
					"originalUrl": "/toys/~minimum-40-percent-off/pr?sid=mgl",
					"url": "/toys/~minimum-40-percent-off/pr?sid=mgl",
					"params": {
						"store": "t06",
						"filter": "filter=facets.promo%255B%255D%3DFreebieOfferOnInternationalBeautyProduct.",
						"valid": true
					}
				},
				"value": {
					"image": {
						"240": "http://img5a.flixcart.com/www/promos/new/20140520-160716-mobile-small.jpg",
						"320": "http://img6a.flixcart.com/www/promos/new/20140520-160716-mobile-medium.jpg",
						"480": "http://img5a.flixcart.com/www/promos/new/20140520-160716-mobile-large.jpg",
						"720": "http://img5a.flixcart.com/www/promos/new/20140520-160716-mobile-extra-large.jpg"
					},
					"source": "config"
				}
			}],
			"type": "BannerWidget",
			"ts": 1400604241119,
			"pageNumber": 1,
			"slotNumber": 0,
			"title": null
		}, {
			"type": "NewLaunchWidget",
			"pageNumber": -1,
			"slotNumber": -1,
			"title": "NewLaunch",
			"items": [{
				"action": {
					"screenType": "webView",
					"params": {
						"url": "http://m.flipkart.com/motorola/motoe"
					},
					"omnitureData": "NewLaunchWidget"
				},
				"value": {
					"image": {
						"240": "http://img6a.flixcart.com/www/promos/new/20140515-140333-moto-emdpi.png",
						"320": "http://img6a.flixcart.com/www/promos/new/20140515-140333-moto-ehdpi.png",
						"480": "http://img5a.flixcart.com/www/promos/new/20140515-140333-moto-exxhdpi.png",
						"720": "http://img5a.flixcart.com/www/promos/new/20140515-140333-moto-exxhdpi.png",
						"wp480": "http://img5a.flixcart.com/www/promos/new/20140515-140333-moto-exxhdpi.png",
						"wp1080": "http://img5a.flixcart.com/www/promos/new/20140515-140333-moto-exxhdpi.png"
					},
					"title": "Moto E: Priced for All!",
					"subTitle": "Exclusively on Flipkart!"
				}
			}],
			"ts": 1400604242301,
			"id": "6f46e97963bd2cad595a0477433b5c70"
		}, {
			"type": "TitleWidget",
			"pageNumber": 0,
			"slotNumber": 0,
			"title": "departments",
			"items": [{
				"value": {
					"heading": "Shop by Departments",
					"items": [{
						"type": "MetroTileExpandableWidget",
						"items": [{
							"action": {
								"screenType": ".expand",
								"omnitureData": "MetroTileExpandableWidget"
							},
							"value": {
								"image": {
									"240": "http://img5a.flixcart.com/www/promos/new/20140424-195900-ldpi.jpg",
									"320": "http://img6a.flixcart.com/www/promos/new/20140424-195900-mdpi.jpg",
									"480": "http://img5a.flixcart.com/www/promos/new/20140424-195900-hdpi.jpg",
									"720": "http://img6a.flixcart.com/www/promos/new/20140424-195900-xhdpi.jpg",
									"wp480": "http://img5a.flixcart.com/www/promos/new/20140303-164401-lifestyle.jpg"
								},
								"title": "Fashion & Lifestyle",
								"items": [{
									"action": {
										"screenType": "multiWidgetPage",
										"params": {
											"screenName": "storefront",
											"store": "men"
										},
										"omnitureData": "MetroTileExpandableWidget"
									},
									"value": {
										"isExpandable": false,
										"isInViewMore": false,
										"autoExpand": false,
										"itemText": "Men",
										"items": []
									}
								}, {
									"action": {
										"screenType": "multiWidgetPage",
										"params": {
											"screenName": "storefront",
											"store": "women"
										},
										"omnitureData": "MetroTileExpandableWidget"
									},
									"value": {
										"isExpandable": false,
										"isInViewMore": false,
										"autoExpand": false,
										"itemText": "Women",
										"items": []
									}
								}, {
									"action": {
										"screenType": "multiWidgetPage",
										"params": {
											"screenName": "storefront",
											"store": "baby"
										},
										"omnitureData": "MetroTileExpandableWidget"
									},
									"value": {
										"isExpandable": false,
										"isInViewMore": false,
										"autoExpand": false,
										"itemText": "Kids & Baby Care",
										"items": []
									}
								}, {
									"action": {
										"screenType": "multiWidgetPage",
										"params": {
											"screenName": "clp",
											"store": "t06"
										},
										"omnitureData": "MetroTileExpandableWidget"
									},
									"value": {
										"isExpandable": false,
										"isInViewMore": false,
										"autoExpand": false,
										"itemText": "Beauty & Personal Care",
										"items": []
									}
								}, {
									"action": {
										"screenType": "multiWidgetPage",
										"params": {
											"screenName": "clp",
											"store": "dep"
										},
										"omnitureData": "MetroTileExpandableWidget"
									},
									"value": {
										"isExpandable": false,
										"isInViewMore": false,
										"autoExpand": false,
										"itemText": "Sports & Fitness",
										"items": []
									}
								}, {
									"action": {
										"screenType": "multiWidgetPage",
										"params": {
											"screenName": "clp",
											"store": "vdm"
										},
										"omnitureData": "MetroTileExpandableWidget"
									},
									"value": {
										"isExpandable": false,
										"isInViewMore": false,
										"autoExpand": false,
										"itemText": "Home Furnishing",
										"items": []
									}
								}, {
									"action": {
										"screenType": "productListView",
										"params": {
											"store": "reh/plk"
										},
										"omnitureData": "MetroTileExpandableWidget"
									},
									"value": {
										"isExpandable": false,
										"isInViewMore": false,
										"autoExpand": false,
										"itemText": "Luggage & Travel",
										"items": []
									}
								}]
							}
						}, {
							"action": {
								"screenType": "multiWidgetPage",
								"params": {
									"screenName": "storefront",
									"store": "electronics"
								},
								"omnitureData": "MetroTileExpandableWidget"
							},
							"value": {
								"image": {
									"240": "http://img5a.flixcart.com/www/promos/new/20140424-200057-ldpi.jpg",
									"320": "http://img5a.flixcart.com/www/promos/new/20140424-200057-mdpi.jpg",
									"480": "http://img6a.flixcart.com/www/promos/new/20140424-200057-hdpi.jpg",
									"720": "http://img5a.flixcart.com/www/promos/new/20140424-200057-xhdpi.jpg",
									"wp480": "http://img6a.flixcart.com/www/promos/new/20140303-164401-electronics.jpg"
								},
								"title": "Electronics"
							}
						}, {
							"action": {
								"screenType": "multiWidgetPage",
								"params": {
									"screenName": "storefront",
									"store": "books"
								},
								"omnitureData": "MetroTileExpandableWidget"
							},
							"value": {
								"image": {
									"240": "http://img6a.flixcart.com/www/promos/new/20140424-200246-ldpi.jpg",
									"320": "http://img6a.flixcart.com/www/promos/new/20140424-200246-mdpi.jpg",
									"480": "http://img6a.flixcart.com/www/promos/new/20140424-200246-hdpi.jpg",
									"720": "http://img6a.flixcart.com/www/promos/new/20140424-200246-xhdpi.jpg",
									"wp480": "http://img5a.flixcart.com/www/promos/new/20140303-164401-books.jpg"
								},
								"title": "Books & More"
							}
						}]
					}]
				},
				"action": {
					"omnitureData": "TitleWidget"
				}
			}],
			"ts": 1400604242301,
			"id": "3fac54eb63be2bd1eae1bbfb8c0745b6"
		}, {
			"items": [{
				"action": {
					"screenType": "webView",
					"omnitureData": null,
					"originalUrl": null,
					"url": "http://www.flipkart.com/m/offers",
					"params": {
						"url": "http://www.flipkart.com/m/offers"
					}
				},
				"value": {
					"heading": "Save Big!!",
					"image": {
						"240": "http://img1a.flixcart.com//www/promos/new/20130711-202112-offer-icon-240.png",
						"480": "http://img1a.flixcart.com//www/promos/new/20130711-202207-offer-icon-480.png",
						"720": "http://img1a.flixcart.com//www/promos/new/20130711-202226-offer-icon-720.png",
						"320": "http://img1a.flixcart.com//www/promos/new/20130711-202133-offer-icon-320.png"
					},
					"items": [{
						"items": [{
							"action": {
								"screenType": "productListView",
								"omnitureData": "OfferZoneWidget",
								"originalUrl": "/promotion/pr?offer=MensFootwear_Extra37.&sid=osp,cil",
								"url": "/promotion/pr?offer=MensFootwear_Extra37.&sid=osp,cil",
								"params": {
									"store": "osp/cil",
									"filter": "filter=facets.promo%255B%255D%3DMensFootwear_Extra37.",
									"offerId": "MensFootwear_Extra37"
								}
							},
							"value": {
								"title": "Men's Footwear - Extra 37% off",
								"source": "santa",
								"isDOTD": false
							}
						}, {
							"action": {
								"screenType": "productListView",
								"omnitureData": "OfferZoneWidget",
								"originalUrl": "/promotion/pr?offer=iPadExchange.&sid=tyy,hry",
								"url": "/promotion/pr?offer=iPadExchange.&sid=tyy,hry",
								"params": {
									"store": "tyy/hry",
									"filter": "filter=facets.promo%255B%255D%3DiPadExchange.",
									"offerId": "iPadExchange"
								}
							},
							"value": {
								"title": "Tablets - ExchangeOffer",
								"source": "santa",
								"isDOTD": false
							}
						}, {
							"action": {
								"screenType": "productListView",
								"omnitureData": "OfferZoneWidget",
								"originalUrl": "/promotion/pr?offer=MultitierLaptop_Offer_Main.&sid=6bo,b5g",
								"url": "/promotion/pr?offer=MultitierLaptop_Offer_Main.&sid=6bo,b5g",
								"params": {
									"store": "6bo/b5g",
									"filter": "filter=facets.promo%255B%255D%3DMultitierLaptop_Offer_Main.",
									"offerId": "MultitierLaptop_Offer_Main"
								}
							},
							"value": {
								"title": "Min Rs. 899 off on Select Laptops",
								"source": "santa",
								"isDOTD": false
							}
						}, {
							"action": {
								"screenType": "productListView",
								"omnitureData": "OfferZoneWidget",
								"originalUrl": "/promotion/pr?offer=DOTDOnPokerCardGames.&sid=mgl,jmb",
								"url": "/promotion/pr?offer=DOTDOnPokerCardGames.&sid=mgl,jmb",
								"params": {
									"store": "mgl/jmb",
									"filter": "filter=facets.promo%255B%255D%3DDOTDOnPokerCardGames.",
									"valid": true
								}
							},
							"value": {
								"title": "Extra 40% off - Poker Card Games",
								"source": "lego",
								"isDOTD": true
							}
						}],
						"type": "OfferZoneWidget",
						"ts": 1400604242298,
						"pageNumber": -1,
						"slotNumber": -1,
						"title": null
					}]
				}
			}],
			"type": "OfferTitleWidget",
			"ts": 1400604242298,
			"pageNumber": 1,
			"slotNumber": 1,
			"title": "save big"
		}, {
			"type": "TitleWidget",
			"pageNumber": 2,
			"slotNumber": 0,
			"title": "hot on flipkart",
			"items": [{
				"value": {
					"heading": "Hot on Flipkart",
					"items": [{
						"type": "SMU6",
						"items": [{
							"action": {
								"screenType": "productListView",
								"params": {
									"store": "tyy/4io",
									"tag": "tag=tags%255B%255D%3Dmoto-g-original-accessories",
									"sort": "sort=popularity"
								},
								"omnitureData": "SMU6"
							},
							"value": {
								"imageProductId": "MOBDSGU2ZMDYENQA",
								"text_line_1": "Moto G",
								"text_line_2": "Only on",
								"text_line_3": "Flipkart",
								"image": {
									"s100": {
										"id": "IMADSMBWHZNHUCJJ",
										"s3_path": "http://img6a.flixcart.com/image/mobile/n/q/a/motorola-moto-g-100x100-imadsmbwhznhucjj.jpeg",
										"actual_width": 52,
										"actual_height": 100,
										"expected_width": 100,
										"expected_height": 100,
										"big_url": "/m/product-ajax/showLargeImage?pid=MOBDSGU2ZMDYENQA&imageId=IMADSMBWHZNHUCJJ"
									},
									"s1100": {
										"id": "IMADSMBWHZNHUCJJ",
										"s3_path": "http://img6a.flixcart.com/image/mobile/n/q/a/motorola-moto-g-1100x1100-imadsmbwhznhucjj.jpeg",
										"actual_width": 567,
										"actual_height": 1100,
										"expected_width": 1100,
										"expected_height": 1100,
										"big_url": "/m/product-ajax/showLargeImage?pid=MOBDSGU2ZMDYENQA&imageId=IMADSMBWHZNHUCJJ"
									},
									"s125": {
										"id": "IMADSMBWHZNHUCJJ",
										"s3_path": "http://img6a.flixcart.com/image/mobile/n/q/a/motorola-moto-g-125x125-imadsmbwhznhucjj.jpeg",
										"actual_width": 64,
										"actual_height": 125,
										"expected_width": 125,
										"expected_height": 125,
										"big_url": "/m/product-ajax/showLargeImage?pid=MOBDSGU2ZMDYENQA&imageId=IMADSMBWHZNHUCJJ"
									},
									"s200": {
										"id": "IMADSMBWHZNHUCJJ",
										"s3_path": "http://img6a.flixcart.com/image/mobile/n/q/a/motorola-moto-g-200x200-imadsmbwhznhucjj.jpeg",
										"actual_width": 103,
										"actual_height": 200,
										"expected_width": 200,
										"expected_height": 200,
										"big_url": "/m/product-ajax/showLargeImage?pid=MOBDSGU2ZMDYENQA&imageId=IMADSMBWHZNHUCJJ"
									},
									"s275": {
										"id": "IMADSMBWHZNHUCJJ",
										"s3_path": "http://img6a.flixcart.com/image/mobile/n/q/a/motorola-moto-g-275x275-imadsmbwhznhucjj.jpeg",
										"actual_width": 142,
										"actual_height": 275,
										"expected_width": 275,
										"expected_height": 275,
										"big_url": "/m/product-ajax/showLargeImage?pid=MOBDSGU2ZMDYENQA&imageId=IMADSMBWHZNHUCJJ"
									},
									"s400": {
										"id": "IMADSMBWHZNHUCJJ",
										"s3_path": "http://img6a.flixcart.com/image/mobile/n/q/a/motorola-moto-g-400x400-imadsmbwhznhucjj.jpeg",
										"actual_width": 206,
										"actual_height": 400,
										"expected_width": 400,
										"expected_height": 400,
										"big_url": "/m/product-ajax/showLargeImage?pid=MOBDSGU2ZMDYENQA&imageId=IMADSMBWHZNHUCJJ"
									},
									"s40": {
										"id": "IMADSMBWHZNHUCJJ",
										"s3_path": "http://img6a.flixcart.com/image/mobile/n/q/a/motorola-moto-g-40x40-imadsmbwhznhucjj.jpeg",
										"actual_width": 21,
										"actual_height": 40,
										"expected_width": 40,
										"expected_height": 40,
										"big_url": "/m/product-ajax/showLargeImage?pid=MOBDSGU2ZMDYENQA&imageId=IMADSMBWHZNHUCJJ"
									},
									"s75": {
										"id": "IMADSMBWHZNHUCJJ",
										"s3_path": "http://img6a.flixcart.com/image/mobile/n/q/a/motorola-moto-g-75x75-imadsmbwhznhucjj.jpeg",
										"actual_width": 39,
										"actual_height": 75,
										"expected_width": 75,
										"expected_height": 75,
										"big_url": "/m/product-ajax/showLargeImage?pid=MOBDSGU2ZMDYENQA&imageId=IMADSMBWHZNHUCJJ"
									},
									"original": {
										"id": "IMADSMBWHZNHUCJJ",
										"s3_path": "http://img6a.flixcart.com/image/mobile/n/q/a/motorola-moto-g-original-imadsmbwhznhucjj.jpeg",
										"actual_width": 2544,
										"actual_height": 4935,
										"expected_width": 2544,
										"expected_height": 4935,
										"big_url": "/m/product-ajax/showLargeImage?pid=MOBDSGU2ZMDYENQA&imageId=IMADSMBWHZNHUCJJ"
									}
								}
							}
						}, {
							"action": {
								"screenType": "productListView",
								"params": {
									"store": "6bo/jdy/nl6",
									"filter": "filter=facets.capacity%5B%5D%3D1%2BTB",
									"sort": "sort=popularity"
								},
								"omnitureData": "SMU6"
							},
							"value": {
								"imageProductId": "ACCD72ZXFC6ZRTST",
								"text_line_1": "Starting From",
								"text_line_2": "Rs. 3700",
								"text_line_3": "1 TB Hard Disks",
								"image": {
									"s100": {
										"id": "IMAD72P52GR6XGTV",
										"s3_path": "http://img5a.flixcart.com//image/external-hard-drive/t/s/t/transcend-storejet-25m3-100x100-imad72p52gr6xgtv.jpeg",
										"actual_width": 65,
										"actual_height": 100,
										"expected_width": 100,
										"expected_height": 100,
										"big_url": "/m/product-ajax/showLargeImage?pid=ACCD72ZXFC6ZRTST&imageId=IMAD72P52GR6XGTV"
									},
									"s125": {
										"id": "IMAD72P52GR6XGTV",
										"s3_path": "http://img5a.flixcart.com//image/external-hard-drive/t/s/t/transcend-storejet-25m3-125x125-imad72p52gr6xgtv.jpeg",
										"actual_width": 82,
										"actual_height": 125,
										"expected_width": 125,
										"expected_height": 125,
										"big_url": "/m/product-ajax/showLargeImage?pid=ACCD72ZXFC6ZRTST&imageId=IMAD72P52GR6XGTV"
									},
									"s200": {
										"id": "IMAD72P52GR6XGTV",
										"s3_path": "http://img5a.flixcart.com//image/external-hard-drive/t/s/t/transcend-storejet-25m3-200x200-imad72p52gr6xgtv.jpeg",
										"actual_width": 131,
										"actual_height": 200,
										"expected_width": 200,
										"expected_height": 200,
										"big_url": "/m/product-ajax/showLargeImage?pid=ACCD72ZXFC6ZRTST&imageId=IMAD72P52GR6XGTV"
									},
									"s275": {
										"id": "IMAD72P52GR6XGTV",
										"s3_path": "http://img5a.flixcart.com//image/external-hard-drive/t/s/t/transcend-storejet-25m3-275x275-imad72p52gr6xgtv.jpeg",
										"actual_width": 180,
										"actual_height": 275,
										"expected_width": 275,
										"expected_height": 275,
										"big_url": "/m/product-ajax/showLargeImage?pid=ACCD72ZXFC6ZRTST&imageId=IMAD72P52GR6XGTV"
									},
									"s400": {
										"id": "IMAD72P52GR6XGTV",
										"s3_path": "http://img5a.flixcart.com//image/external-hard-drive/t/s/t/transcend-storejet-25m3-400x400-imad72p52gr6xgtv.jpeg",
										"actual_width": 262,
										"actual_height": 400,
										"expected_width": 400,
										"expected_height": 400,
										"big_url": "/m/product-ajax/showLargeImage?pid=ACCD72ZXFC6ZRTST&imageId=IMAD72P52GR6XGTV"
									},
									"s40": {
										"id": "IMAD72P52GR6XGTV",
										"s3_path": "http://img5a.flixcart.com//image/external-hard-drive/t/s/t/transcend-storejet-25m3-40x40-imad72p52gr6xgtv.jpeg",
										"actual_width": 26,
										"actual_height": 40,
										"expected_width": 40,
										"expected_height": 40,
										"big_url": "/m/product-ajax/showLargeImage?pid=ACCD72ZXFC6ZRTST&imageId=IMAD72P52GR6XGTV"
									},
									"s75": {
										"id": "IMAD72P52GR6XGTV",
										"s3_path": "http://img5a.flixcart.com//image/external-hard-drive/t/s/t/transcend-storejet-25m3-75x75-imad72p52gr6xgtv.jpeg",
										"actual_width": 49,
										"actual_height": 75,
										"expected_width": 75,
										"expected_height": 75,
										"big_url": "/m/product-ajax/showLargeImage?pid=ACCD72ZXFC6ZRTST&imageId=IMAD72P52GR6XGTV"
									},
									"original": {
										"id": "IMAD72P52GR6XGTV",
										"s3_path": "http://img5a.flixcart.com//image/external-hard-drive/t/s/t/transcend-storejet-25m3-original-imad72p52gr6xgtv.jpeg",
										"actual_width": 391,
										"actual_height": 598,
										"expected_width": 391,
										"expected_height": 598,
										"big_url": "/m/product-ajax/showLargeImage?pid=ACCD72ZXFC6ZRTST&imageId=IMAD72P52GR6XGTV"
									}
								}
							}
						}, {
							"action": {
								"screenType": "productListView",
								"params": {
									"store": "osp/iko",
									"tag": "tag=tags%255B%255D%3Dbelow-699",
									"sort": "sort=popularity"
								},
								"omnitureData": "SMU6"
							},
							"value": {
								"imageProductId": "SNDDSGH63EVSKZTF",
								"text_line_1": "Fashion",
								"text_line_2": "Under 699",
								"text_line_3": "Women's Footwear",
								"image": {
									"s100": {
										"id": "IMADUVCQQ4RTZPGU",
										"s3_path": "http://img5a.flixcart.com/image/sandal/z/t/f/yellow-578-nell-40-100x100-imaduvcqq4rtzpgu.jpeg",
										"actual_width": 100,
										"actual_height": 51,
										"expected_width": 100,
										"expected_height": 100,
										"big_url": "/m/product-ajax/showLargeImage?pid=SNDDSGH63EVSKZTF&imageId=IMADUVCQQ4RTZPGU"
									},
									"s1100": {
										"id": "IMADUVCQQ4RTZPGU",
										"s3_path": "http://img5a.flixcart.com/image/sandal/z/t/f/yellow-578-nell-40-1100x1360-imaduvcqq4rtzpgu.jpeg",
										"actual_width": 1100,
										"actual_height": 559,
										"expected_width": 1100,
										"expected_height": 1360,
										"big_url": "/m/product-ajax/showLargeImage?pid=SNDDSGH63EVSKZTF&imageId=IMADUVCQQ4RTZPGU"
									},
									"s125": {
										"id": "IMADUVCQQ4RTZPGU",
										"s3_path": "http://img5a.flixcart.com/image/sandal/z/t/f/yellow-578-nell-40-125x167-imaduvcqq4rtzpgu.jpeg",
										"actual_width": 125,
										"actual_height": 63,
										"expected_width": 125,
										"expected_height": 167,
										"big_url": "/m/product-ajax/showLargeImage?pid=SNDDSGH63EVSKZTF&imageId=IMADUVCQQ4RTZPGU"
									},
									"s180": {
										"id": "IMADUVCQQ4RTZPGU",
										"s3_path": "http://img5a.flixcart.com/image/sandal/z/t/f/yellow-578-nell-40-180x240-imaduvcqq4rtzpgu.jpeg",
										"actual_width": 180,
										"actual_height": 91,
										"expected_width": 180,
										"expected_height": 240,
										"big_url": "/m/product-ajax/showLargeImage?pid=SNDDSGH63EVSKZTF&imageId=IMADUVCQQ4RTZPGU"
									},
									"s200": {
										"id": "IMADUVCQQ4RTZPGU",
										"s3_path": "http://img5a.flixcart.com/image/sandal/z/t/f/yellow-578-nell-40-200x200-imaduvcqq4rtzpgu.jpeg",
										"actual_width": 200,
										"actual_height": 102,
										"expected_width": 200,
										"expected_height": 200,
										"big_url": "/m/product-ajax/showLargeImage?pid=SNDDSGH63EVSKZTF&imageId=IMADUVCQQ4RTZPGU"
									},
									"s275": {
										"id": "IMADUVCQQ4RTZPGU",
										"s3_path": "http://img5a.flixcart.com/image/sandal/z/t/f/yellow-578-nell-40-275x340-imaduvcqq4rtzpgu.jpeg",
										"actual_width": 275,
										"actual_height": 140,
										"expected_width": 275,
										"expected_height": 340,
										"big_url": "/m/product-ajax/showLargeImage?pid=SNDDSGH63EVSKZTF&imageId=IMADUVCQQ4RTZPGU"
									},
									"s400": {
										"id": "IMADUVCQQ4RTZPGU",
										"s3_path": "http://img5a.flixcart.com/image/sandal/z/t/f/yellow-578-nell-40-400x400-imaduvcqq4rtzpgu.jpeg",
										"actual_width": 400,
										"actual_height": 203,
										"expected_width": 400,
										"expected_height": 400,
										"big_url": "/m/product-ajax/showLargeImage?pid=SNDDSGH63EVSKZTF&imageId=IMADUVCQQ4RTZPGU"
									},
									"s40": {
										"id": "IMADUVCQQ4RTZPGU",
										"s3_path": "http://img5a.flixcart.com/image/sandal/z/t/f/yellow-578-nell-40-40x40-imaduvcqq4rtzpgu.jpeg",
										"actual_width": 40,
										"actual_height": 20,
										"expected_width": 40,
										"expected_height": 40,
										"big_url": "/m/product-ajax/showLargeImage?pid=SNDDSGH63EVSKZTF&imageId=IMADUVCQQ4RTZPGU"
									},
									"s700": {
										"id": "IMADUVCQQ4RTZPGU",
										"s3_path": "http://img5a.flixcart.com/image/sandal/z/t/f/yellow-578-nell-40-700x700-imaduvcqq4rtzpgu.jpeg",
										"actual_width": 700,
										"actual_height": 355,
										"expected_width": 700,
										"expected_height": 700,
										"big_url": "/m/product-ajax/showLargeImage?pid=SNDDSGH63EVSKZTF&imageId=IMADUVCQQ4RTZPGU"
									},
									"s75": {
										"id": "IMADUVCQQ4RTZPGU",
										"s3_path": "http://img5a.flixcart.com/image/sandal/z/t/f/yellow-578-nell-40-75x75-imaduvcqq4rtzpgu.jpeg",
										"actual_width": 75,
										"actual_height": 38,
										"expected_width": 75,
										"expected_height": 75,
										"big_url": "/m/product-ajax/showLargeImage?pid=SNDDSGH63EVSKZTF&imageId=IMADUVCQQ4RTZPGU"
									},
									"original": {
										"id": "IMADUVCQQ4RTZPGU",
										"s3_path": "http://img5a.flixcart.com/image/sandal/z/t/f/yellow-578-nell-40-original-imaduvcqq4rtzpgu.jpeg",
										"actual_width": 768,
										"actual_height": 390,
										"expected_width": 768,
										"expected_height": 390,
										"big_url": "/m/product-ajax/showLargeImage?pid=SNDDSGH63EVSKZTF&imageId=IMADUVCQQ4RTZPGU"
									}
								}
							}
						}, {
							"action": {
								"screenType": "productListView",
								"params": {
									"store": "26x",
									"filter": "filter=facets.brand%5B%5D%3DFastrack&filter=facets.discount_range%5B%5D%3DUpto%2B10%252525&filter=facets.discount_range%5B%5D%3D10%252525%2B-%2B20%252525&filter=facets.discount_range%5B%5D%3D20%252525%2B-%2B30%252525&filter=facets.discount_range%5B%5D%3D30%252525%2B-%2B50%252525&filter=facets.discount_range%5B%5D%3DMore%2Bthan%2B50%252525",
									"sort": "sort=popularity"
								},
								"omnitureData": "SMU6"
							},
							"value": {
								"imageProductId": "SGLDPZH3PVDHYD44",
								"text_line_1": "Smart buy",
								"text_line_2": "Fastrack",
								"text_line_3": "Sunglasses",
								"image": {
									"s100": {
										"id": "IMADQAZ5WFMY8BSE",
										"s3_path": "http://img5a.flixcart.com/image/sunglass/d/4/4/m067br4-fastrack-free-size-100x100-imadqaz5wfmy8bse.jpeg",
										"actual_width": 100,
										"actual_height": 64,
										"expected_width": 100,
										"expected_height": 100,
										"big_url": "/m/product-ajax/showLargeImage?pid=SGLDPZH3PVDHYD44&imageId=IMADQAZ5WFMY8BSE"
									},
									"s1100": {
										"id": "IMADQAZ5WFMY8BSE",
										"s3_path": "http://img5a.flixcart.com/image/sunglass/d/4/4/m067br4-fastrack-free-size-1100x1100-imadqaz5wfmy8bse.jpeg",
										"actual_width": 1100,
										"actual_height": 700,
										"expected_width": 1100,
										"expected_height": 1100,
										"big_url": "/m/product-ajax/showLargeImage?pid=SGLDPZH3PVDHYD44&imageId=IMADQAZ5WFMY8BSE"
									},
									"s125": {
										"id": "IMADQAZ5WFMY8BSE",
										"s3_path": "http://img5a.flixcart.com/image/sunglass/d/4/4/m067br4-fastrack-free-size-125x125-imadqaz5wfmy8bse.jpeg",
										"actual_width": 125,
										"actual_height": 80,
										"expected_width": 125,
										"expected_height": 125,
										"big_url": "/m/product-ajax/showLargeImage?pid=SGLDPZH3PVDHYD44&imageId=IMADQAZ5WFMY8BSE"
									},
									"s200": {
										"id": "IMADQAZ5WFMY8BSE",
										"s3_path": "http://img5a.flixcart.com/image/sunglass/d/4/4/m067br4-fastrack-free-size-200x200-imadqaz5wfmy8bse.jpeg",
										"actual_width": 200,
										"actual_height": 127,
										"expected_width": 200,
										"expected_height": 200,
										"big_url": "/m/product-ajax/showLargeImage?pid=SGLDPZH3PVDHYD44&imageId=IMADQAZ5WFMY8BSE"
									},
									"s275": {
										"id": "IMADQAZ5WFMY8BSE",
										"s3_path": "http://img5a.flixcart.com/image/sunglass/d/4/4/m067br4-fastrack-free-size-275x275-imadqaz5wfmy8bse.jpeg",
										"actual_width": 275,
										"actual_height": 175,
										"expected_width": 275,
										"expected_height": 275,
										"big_url": "/m/product-ajax/showLargeImage?pid=SGLDPZH3PVDHYD44&imageId=IMADQAZ5WFMY8BSE"
									},
									"s400": {
										"id": "IMADQAZ5WFMY8BSE",
										"s3_path": "http://img5a.flixcart.com/image/sunglass/d/4/4/m067br4-fastrack-free-size-400x400-imadqaz5wfmy8bse.jpeg",
										"actual_width": 400,
										"actual_height": 255,
										"expected_width": 400,
										"expected_height": 400,
										"big_url": "/m/product-ajax/showLargeImage?pid=SGLDPZH3PVDHYD44&imageId=IMADQAZ5WFMY8BSE"
									},
									"s40": {
										"id": "IMADQAZ5WFMY8BSE",
										"s3_path": "http://img5a.flixcart.com/image/sunglass/d/4/4/m067br4-fastrack-free-size-40x40-imadqaz5wfmy8bse.jpeg",
										"actual_width": 40,
										"actual_height": 25,
										"expected_width": 40,
										"expected_height": 40,
										"big_url": "/m/product-ajax/showLargeImage?pid=SGLDPZH3PVDHYD44&imageId=IMADQAZ5WFMY8BSE"
									},
									"s75": {
										"id": "IMADQAZ5WFMY8BSE",
										"s3_path": "http://img5a.flixcart.com/image/sunglass/d/4/4/m067br4-fastrack-free-size-75x75-imadqaz5wfmy8bse.jpeg",
										"actual_width": 75,
										"actual_height": 48,
										"expected_width": 75,
										"expected_height": 75,
										"big_url": "/m/product-ajax/showLargeImage?pid=SGLDPZH3PVDHYD44&imageId=IMADQAZ5WFMY8BSE"
									},
									"original": {
										"id": "IMADQAZ5WFMY8BSE",
										"s3_path": "http://img5a.flixcart.com/image/sunglass/d/4/4/m067br4-fastrack-free-size-original-imadqaz5wfmy8bse.jpeg",
										"actual_width": 837,
										"actual_height": 533,
										"expected_width": 837,
										"expected_height": 533,
										"big_url": "/m/product-ajax/showLargeImage?pid=SGLDPZH3PVDHYD44&imageId=IMADQAZ5WFMY8BSE"
									}
								}
							}
						}, {
							"action": {
								"screenType": "productListView",
								"params": {
									"store": "bks",
									"tag": "tag=tags%255B%255D%3Dnew-releases-limited",
									"sort": "sort=popularity"
								},
								"omnitureData": "SMU6"
							},
							"value": {
								"imageProductId": "9781447265092",
								"text_line_1": "New Releases ",
								"text_line_2": "Books",
								"text_line_3": "Shop now",
								"image": {
									"s100": {
										"id": "IMADSM4J66ARWURB",
										"s3_path": "http://img6a.flixcart.com/image/book/0/9/2/be-careful-what-you-wish-for-100x100-imadsm4j66arwurb.jpeg",
										"actual_width": 65,
										"actual_height": 100,
										"expected_width": 100,
										"expected_height": 100,
										"big_url": "/m/product-ajax/showLargeImage?pid=9781447265092&imageId=IMADSM4J66ARWURB"
									},
									"s1100": {
										"id": "IMADSM4J66ARWURB",
										"s3_path": "http://img6a.flixcart.com/image/book/0/9/2/be-careful-what-you-wish-for-1100x1100-imadsm4j66arwurb.jpeg",
										"actual_width": 714,
										"actual_height": 1100,
										"expected_width": 1100,
										"expected_height": 1100,
										"big_url": "/m/product-ajax/showLargeImage?pid=9781447265092&imageId=IMADSM4J66ARWURB"
									},
									"s125": {
										"id": "IMADSM4J66ARWURB",
										"s3_path": "http://img6a.flixcart.com/image/book/0/9/2/be-careful-what-you-wish-for-125x125-imadsm4j66arwurb.jpeg",
										"actual_width": 81,
										"actual_height": 125,
										"expected_width": 125,
										"expected_height": 125,
										"big_url": "/m/product-ajax/showLargeImage?pid=9781447265092&imageId=IMADSM4J66ARWURB"
									},
									"s200": {
										"id": "IMADSM4J66ARWURB",
										"s3_path": "http://img6a.flixcart.com/image/book/0/9/2/be-careful-what-you-wish-for-200x200-imadsm4j66arwurb.jpeg",
										"actual_width": 130,
										"actual_height": 200,
										"expected_width": 200,
										"expected_height": 200,
										"big_url": "/m/product-ajax/showLargeImage?pid=9781447265092&imageId=IMADSM4J66ARWURB"
									},
									"s275": {
										"id": "IMADSM4J66ARWURB",
										"s3_path": "http://img6a.flixcart.com/image/book/0/9/2/be-careful-what-you-wish-for-275x275-imadsm4j66arwurb.jpeg",
										"actual_width": 179,
										"actual_height": 275,
										"expected_width": 275,
										"expected_height": 275,
										"big_url": "/m/product-ajax/showLargeImage?pid=9781447265092&imageId=IMADSM4J66ARWURB"
									},
									"s400": {
										"id": "IMADSM4J66ARWURB",
										"s3_path": "http://img6a.flixcart.com/image/book/0/9/2/be-careful-what-you-wish-for-400x400-imadsm4j66arwurb.jpeg",
										"actual_width": 260,
										"actual_height": 400,
										"expected_width": 400,
										"expected_height": 400,
										"big_url": "/m/product-ajax/showLargeImage?pid=9781447265092&imageId=IMADSM4J66ARWURB"
									},
									"s40": {
										"id": "IMADSM4J66ARWURB",
										"s3_path": "http://img6a.flixcart.com/image/book/0/9/2/be-careful-what-you-wish-for-40x40-imadsm4j66arwurb.jpeg",
										"actual_width": 26,
										"actual_height": 40,
										"expected_width": 40,
										"expected_height": 40,
										"big_url": "/m/product-ajax/showLargeImage?pid=9781447265092&imageId=IMADSM4J66ARWURB"
									},
									"s700": {
										"id": "IMADSM4J66ARWURB",
										"s3_path": "http://img6a.flixcart.com/image/book/0/9/2/be-careful-what-you-wish-for-700x700-imadsm4j66arwurb.jpeg",
										"actual_width": 455,
										"actual_height": 700,
										"expected_width": 700,
										"expected_height": 700,
										"big_url": "/m/product-ajax/showLargeImage?pid=9781447265092&imageId=IMADSM4J66ARWURB"
									},
									"s75": {
										"id": "IMADSM4J66ARWURB",
										"s3_path": "http://img6a.flixcart.com/image/book/0/9/2/be-careful-what-you-wish-for-75x75-imadsm4j66arwurb.jpeg",
										"actual_width": 49,
										"actual_height": 75,
										"expected_width": 75,
										"expected_height": 75,
										"big_url": "/m/product-ajax/showLargeImage?pid=9781447265092&imageId=IMADSM4J66ARWURB"
									},
									"original": {
										"id": "IMADSM4J66ARWURB",
										"s3_path": "http://img6a.flixcart.com/image/book/0/9/2/be-careful-what-you-wish-for-original-imadsm4j66arwurb.jpeg",
										"actual_width": 1848,
										"actual_height": 2846,
										"expected_width": 1848,
										"expected_height": 2846,
										"big_url": "/m/product-ajax/showLargeImage?pid=9781447265092&imageId=IMADSM4J66ARWURB"
									}
								}
							}
						}, {
							"action": {
								"screenType": "productListView",
								"params": {
									"version": "2",
									"store": "t06/r3o/aa1",
									"tag": "tag=tags%255B%255D%3Dflat-45",
									"sort": "sort=popularity"
								},
								"omnitureData": "SMU6"
							},
							"value": {
								"imageProductId": "PERD8DHUZFQ24YFY",
								"text_line_1": "Flat",
								"text_line_2": "45% Off",
								"text_line_3": "Perfumes",
								"image": {
									"s100": {
										"id": "IMADU5HV35ERVSGZ",
										"s3_path": "http://img6a.flixcart.com/image/perfume/y/f/y/eau-de-toilette-davidoff-125-cool-water-100x100-imadu5hv35ervsgz.jpeg",
										"actual_width": 67,
										"actual_height": 100,
										"expected_width": 100,
										"expected_height": 100,
										"big_url": "/m/product-ajax/showLargeImage?pid=PERD8DHUZFQ24YFY&imageId=IMADU5HV35ERVSGZ"
									},
									"s1100": {
										"id": "IMADU5HV35ERVSGZ",
										"s3_path": "http://img6a.flixcart.com/image/perfume/y/f/y/eau-de-toilette-davidoff-125-cool-water-1100x1100-imadu5hv35ervsgz.jpeg",
										"actual_width": 742,
										"actual_height": 1100,
										"expected_width": 1100,
										"expected_height": 1100,
										"big_url": "/m/product-ajax/showLargeImage?pid=PERD8DHUZFQ24YFY&imageId=IMADU5HV35ERVSGZ"
									},
									"s125": {
										"id": "IMADU5HV35ERVSGZ",
										"s3_path": "http://img6a.flixcart.com/image/perfume/y/f/y/eau-de-toilette-davidoff-125-cool-water-125x125-imadu5hv35ervsgz.jpeg",
										"actual_width": 84,
										"actual_height": 125,
										"expected_width": 125,
										"expected_height": 125,
										"big_url": "/m/product-ajax/showLargeImage?pid=PERD8DHUZFQ24YFY&imageId=IMADU5HV35ERVSGZ"
									},
									"s200": {
										"id": "IMADU5HV35ERVSGZ",
										"s3_path": "http://img6a.flixcart.com/image/perfume/y/f/y/eau-de-toilette-davidoff-125-cool-water-200x200-imadu5hv35ervsgz.jpeg",
										"actual_width": 135,
										"actual_height": 200,
										"expected_width": 200,
										"expected_height": 200,
										"big_url": "/m/product-ajax/showLargeImage?pid=PERD8DHUZFQ24YFY&imageId=IMADU5HV35ERVSGZ"
									},
									"s275": {
										"id": "IMADU5HV35ERVSGZ",
										"s3_path": "http://img6a.flixcart.com/image/perfume/y/f/y/eau-de-toilette-davidoff-125-cool-water-275x275-imadu5hv35ervsgz.jpeg",
										"actual_width": 186,
										"actual_height": 275,
										"expected_width": 275,
										"expected_height": 275,
										"big_url": "/m/product-ajax/showLargeImage?pid=PERD8DHUZFQ24YFY&imageId=IMADU5HV35ERVSGZ"
									},
									"s400": {
										"id": "IMADU5HV35ERVSGZ",
										"s3_path": "http://img6a.flixcart.com/image/perfume/y/f/y/eau-de-toilette-davidoff-125-cool-water-400x400-imadu5hv35ervsgz.jpeg",
										"actual_width": 270,
										"actual_height": 400,
										"expected_width": 400,
										"expected_height": 400,
										"big_url": "/m/product-ajax/showLargeImage?pid=PERD8DHUZFQ24YFY&imageId=IMADU5HV35ERVSGZ"
									},
									"s40": {
										"id": "IMADU5HV35ERVSGZ",
										"s3_path": "http://img6a.flixcart.com/image/perfume/y/f/y/eau-de-toilette-davidoff-125-cool-water-40x40-imadu5hv35ervsgz.jpeg",
										"actual_width": 27,
										"actual_height": 40,
										"expected_width": 40,
										"expected_height": 40,
										"big_url": "/m/product-ajax/showLargeImage?pid=PERD8DHUZFQ24YFY&imageId=IMADU5HV35ERVSGZ"
									},
									"s75": {
										"id": "IMADU5HV35ERVSGZ",
										"s3_path": "http://img6a.flixcart.com/image/perfume/y/f/y/eau-de-toilette-davidoff-125-cool-water-75x75-imadu5hv35ervsgz.jpeg",
										"actual_width": 51,
										"actual_height": 75,
										"expected_width": 75,
										"expected_height": 75,
										"big_url": "/m/product-ajax/showLargeImage?pid=PERD8DHUZFQ24YFY&imageId=IMADU5HV35ERVSGZ"
									},
									"original": {
										"id": "IMADU5HV35ERVSGZ",
										"s3_path": "http://img6a.flixcart.com/image/perfume/y/f/y/eau-de-toilette-davidoff-125-cool-water-original-imadu5hv35ervsgz.jpeg",
										"actual_width": 742,
										"actual_height": 1100,
										"expected_width": 742,
										"expected_height": 1100,
										"big_url": "/m/product-ajax/showLargeImage?pid=PERD8DHUZFQ24YFY&imageId=IMADU5HV35ERVSGZ"
									}
								}
							}
						}]
					}]
				},
				"action": {
					"omnitureData": "TitleWidget"
				}
			}],
			"ts": 1400604242301,
			"id": "c3c57a8613f070293d96df698d4e1bf7"
		}, {
			"type": "TitleWidget",
			"pageNumber": 3,
			"slotNumber": 0,
			"title": "recently viewed",
			"items": [{
				"value": {
					"heading": "You recently viewed",
					"items": [{
						"type": "PMU",
						"items": [{
							"action": {
								"screenType": "productListView",
								"params": {},
								"omnitureData": "PMU"
							},
							"value": {
								"src": "client",
								"title": "BrowseHistory",
								"items": []
							}
						}]
					}]
				},
				"action": {
					"screenType": "productListView",
					"params": {
						"dataType": "BrowseHistory",
						"title": "Recently viewed"
					},
					"omnitureData": "TitleWidget"
				}
			}],
			"ts": 1400604242301,
			"id": "872dca36b2104d64a5936e96b05a5927"
		}]
	},
	"SESSION": {
		"nsid": "2.SI72D25EA28CFC437C8AF419E0465C08E8.1400604610.VI1B0D1D5C8E6945518048692A639FA9A3",
		"vid": "2.VI1B0D1D5C8E6945518048692A639FA9A3.1400604610.VS777CB57CF772447384A4D2A5CE741EF5",
		"sn": "2.VI1B0D1D5C8E6945518048692A639FA9A3.SI72D25EA28CFC437C8AF419E0465C08E8.VS777CB57CF772447384A4D2A5CE741EF5.1400604610",
		"ts": 0,
		"email": null,
		"firstName": null,
		"lastName": null,
		"accountId": null,
		"secureToken": "SI72D25EA28CFC437C8AF419E0465C08E8:VI1B0D1D5C8E6945518048692A639FA9A3",
		"isLoggedIn": false
	}
}